{
	"name": "athena",
	"properties": {
		"activities": [
			{
				"name": "Web1",
				"type": "WebActivity",
				"dependsOn": [],
				"policy": {
					"timeout": "0.12:00:00",
					"retry": 0,
					"retryIntervalInSeconds": 30,
					"secureOutput": false,
					"secureInput": false
				},
				"userProperties": [],
				"typeProperties": {
					"url": "https://athena.hive2.digital4danone.com/api/scenarios/demand_overview/",
					"method": "GET",
					"authentication": {
						"type": "Basic",
						"username": "connect2.0@danone.com",
						"password": {
							"type": "SecureString",
							"value": "**********"
						}
					}
				}
			}
		],
		"annotations": []
	}
}